paprwall/__init__.py
paprwall/__version__.py
paprwall/cli.py
paprwall/core.py
paprwall/installer.py
paprwall/post_install.py
paprwall/service.py
paprwall/gui/__init__.py
paprwall/gui/wallpaper_manager_gui.py
paprwall-2.1.1.dist-info/licenses/LICENSE
paprwall-2.1.1.dist-info/METADATA
paprwall-2.1.1.dist-info/WHEEL
paprwall-2.1.1.dist-info/entry_points.txt
paprwall-2.1.1.dist-info/top_level.txt
paprwall-2.1.1.dist-info/RECORD
