Metadata-Version: 2.4
Name: paprwall
Version: 2.1.1
Summary: Modern Desktop Wallpaper Manager with Motivational Quotes
Author-email: riturajprofile <riturajprofile.me@gmail.com>
License: CC BY-NC 4.0
Project-URL: Homepage, https://www.riturajprofile.me
Project-URL: Repository, https://github.com/riturajprofile/paprwall
Project-URL: Documentation, https://github.com/riturajprofile/paprwall#readme
Project-URL: Bug Tracker, https://github.com/riturajprofile/paprwall/issues
Project-URL: Changelog, https://github.com/riturajprofile/paprwall/releases
Project-URL: LinkedIn, https://www.linkedin.com/in/riturajprofile
Keywords: wallpaper,desktop,gui,quotes,automation,linux,windows
Classifier: Development Status :: 5 - Production/Stable
Classifier: Intended Audience :: End Users/Desktop
Classifier: Operating System :: OS Independent
Classifier: Programming Language :: Python :: 3
Classifier: Programming Language :: Python :: 3.9
Classifier: Programming Language :: Python :: 3.10
Classifier: Programming Language :: Python :: 3.11
Classifier: Programming Language :: Python :: 3.12
Classifier: Topic :: Desktop Environment
Classifier: Topic :: Multimedia :: Graphics :: Viewers
Classifier: Environment :: X11 Applications
Classifier: License :: Free for non-commercial use
Requires-Python: >=3.9
License-File: LICENSE
Requires-Dist: requests>=2.28.0
Requires-Dist: Pillow>=10.0.0
Provides-Extra: build
Requires-Dist: pyinstaller>=5.0; extra == "build"
Requires-Dist: cx-freeze>=6.0; extra == "build"
Requires-Dist: build; extra == "build"
Requires-Dist: twine; extra == "build"
Provides-Extra: dev
Requires-Dist: pytest>=7.0; extra == "dev"
Requires-Dist: pytest-cov; extra == "dev"
Requires-Dist: black; extra == "dev"
Requires-Dist: flake8; extra == "dev"
Requires-Dist: mypy; extra == "dev"
Requires-Dist: isort; extra == "dev"
Requires-Dist: types-requests; extra == "dev"
Dynamic: license-file
